turbo_boot/__init__.py
turbo_boot/config_loader.py
turbo_boot/http_methods.py
turbo_boot/logging.py
turbo_boot/logging_level.py
turbo_boot/rest_controller.py
turbo_boot/singleton_meta.py
turbo_boot/turbo_boot.py
turbo_boot-0.1.9.dist-info/METADATA
turbo_boot-0.1.9.dist-info/WHEEL
turbo_boot-0.1.9.dist-info/RECORD
